<?xml version="1.0" encoding="utf-8"?>
<publishData>
  <publishProfile publishUrl="E:\公司\宇帆科技\公司网站\发布" deleteExistingFiles="False" ftpAnonymousLogin="False" ftpPassiveMode="True" msdeploySite="" msdeploySiteID="" msdeployRemoteSitePhysicalPath="" msdeployAllowUntrustedCertificate="False" msdeploySkipExtraFilesOnServer="True" msdeployMarkAsApp="False" profileName="本地发布" publishMethod="FileSystem" replaceMatchingFiles="True" userName="" savePWD="False" userPWD="" SelectedForPublish="True">
    <file relUrl="ckfinder/core/skins/default/images/toolbar.collapse.gif" publishTime="01/11/2010 14:32:34" />
    <file relUrl="ckfinder/core/help/es/files/006.html" publishTime="01/04/2010 13:39:26" />
    <file relUrl="Admin/Ad/AdAdmin.aspx" publishTime="02/21/2010 22:10:28" />
    <file relUrl="ckeditor/plugins/forms/dialogs/form.js" publishTime="09/21/2010 16:52:06" />
    <file relUrl="ckeditor/skins/kama/images/toolbar_start.gif" publishTime="09/21/2010 16:52:06" />
    <file relUrl="ckfinder/core/images/icons/32/mdb.gif" publishTime="01/11/2010 14:32:34" />
    <file relUrl="ckeditor/plugins/forms/dialogs/hiddenfield.js" publishTime="09/21/2010 16:52:06" />
    <file relUrl="ckeditor/ckeditor_basic_source.js" publishTime="09/21/2010 16:52:06" />
    <file relUrl="OrderList.aspx" publishTime="10/14/2010 00:11:51" />
    <file relUrl="ckeditor/CHANGES.html" publishTime="09/21/2010 16:52:06" />
    <file relUrl="ckfinder/core/images/icons/16/doc.gif" publishTime="01/11/2010 14:32:34" />
    <file relUrl="ckfinder/core/help/es/files/images/001.png" publishTime="01/11/2010 14:32:32" />
    <file relUrl="ckfinder/core/images/icons/32/mp3.gif" publishTime="01/11/2010 14:32:34" />
    <file relUrl="ckfinder/core/connector/aspx/lang/fr.xml" publishTime="01/06/2010 10:27:58" />
    <file relUrl="ckeditor/plugins/wsc/dialogs/wsc.js" publishTime="09/21/2010 16:52:06" />
    <file relUrl="ckfinder/core/help/es/index.html" publishTime="01/04/2010 13:39:26" />
    <file relUrl="ckfinder/core/images/icons/16/rdp.gif" publishTime="01/11/2010 14:32:34" />
    <file relUrl="Images/3n.gif" publishTime="04/24/2003 11:49:10" />
    <file relUrl="ckeditor/skins/office2003/images/dialog_sides_rtl.png" publishTime="09/21/2010 16:52:06" />
    <file relUrl="ckfinder/ckfinder.js" publishTime="09/10/2010 17:30:17" />
    <file relUrl="ckeditor/skins/v2/images/noimage.png" publishTime="09/21/2010 16:52:06" />
    <file relUrl="ckfinder/core/help/es/files/images/002.gif" publishTime="01/11/2010 14:32:32" />
    <file relUrl="ckfinder/core/images/ckfminus.gif" publishTime="01/11/2010 14:32:34" />
    <file relUrl="ckfinder/core/help/en/files/images/011.gif" publishTime="01/11/2010 14:32:32" />
    <file relUrl="ckfinder/core/connector/aspx/lang/ru.xml" publishTime="01/06/2010 10:27:58" />
    <file relUrl="ckfinder/core/help/es/files/images/011.png" publishTime="01/11/2010 14:32:32" />
    <file relUrl="ckfinder/core/help/en/files/009.html" publishTime="01/04/2010 13:39:24" />
    <file relUrl="bin/Eisp.DAL.dll" publishTime="02/25/2013 23:22:26" />
    <file relUrl="Admin/Images/crm_15.gif" publishTime="08/18/2008 20:12:42" />
    <file relUrl="ckfinder/core/help/es-mx/files/002.html" publishTime="01/04/2010 13:39:28" />
    <file relUrl="ckeditor/skins/kama/images/dialog_sides.png" publishTime="09/21/2010 16:52:06" />
    <file relUrl="ckeditor/plugins/flash/images/placeholder.png" publishTime="09/21/2010 16:52:06" />
    <file relUrl="Admin/Images/Admin_Default/SortEnd_Folder_Open.gif" publishTime="05/16/2009 11:12:38" />
    <file relUrl="Images/new.gif" publishTime="09/01/2008 23:36:34" />
    <file relUrl="ckfinder/core/connector/aspx/lang/cs.xml" publishTime="01/06/2010 10:27:58" />
    <file relUrl="ckfinder/core/images/icons/16/vsd.gif" publishTime="01/11/2010 14:32:34" />
    <file relUrl="ckfinder/core/connector/aspx/lang/lv.xml" publishTime="01/06/2010 10:27:58" />
    <file relUrl="ckeditor/skins/office2003/images/sprites.png" publishTime="09/21/2010 16:52:06" />
    <file relUrl="Admin/Downloads/DownloadAdd.aspx" publishTime="10/14/2010 12:59:58" />
    <file relUrl="Admin/Images/Admin_Default/admin_title_bg_quit.gif" publishTime="12/08/2005 15:52:26" />
    <file relUrl="ckfinder/core/help/es/files/images/018.png" publishTime="01/11/2010 14:32:32" />
    <file relUrl="ckfinder/core/help/en/files/001.html" publishTime="01/04/2010 13:39:24" />
    <file relUrl="ckeditor/skins/office2003/images/mini.gif" publishTime="09/21/2010 16:52:06" />
    <file relUrl="bin/en/AspNetPager.resources.dll" publishTime="02/25/2013 23:22:26" />
    <file relUrl="ckfinder/core/images/icons/16/exe.gif" publishTime="01/11/2010 14:32:34" />
    <file relUrl="Admin/Images/crm_22.gif" publishTime="08/18/2008 20:12:44" />
    <file relUrl="Images/prevg.gif" publishTime="04/24/2003 13:12:50" />
    <file relUrl="Admin/LeftFrame.aspx" publishTime="09/21/2010 12:57:54" />
    <file relUrl="bin/Eisp.Common.dll" publishTime="02/25/2013 23:22:25" />
    <file relUrl="ckfinder/core/help/pl/files/002.html" publishTime="01/04/2010 13:39:30" />
    <file relUrl="license.txt" publishTime="03/12/2010 16:45:58" />
    <file relUrl="ckfinder/core/images/icons/16/fla.gif" publishTime="01/11/2010 14:32:34" />
    <file relUrl="Images/lastn.gif" publishTime="04/30/2003 15:06:02" />
    <file relUrl="ckfinder/core/help/es/files/007.html" publishTime="01/04/2010 13:39:26" />
    <file relUrl="Admin/Images/Admin_Default/admin_www.gif" publishTime="12/30/2004 19:21:18" />
    <file relUrl="ckeditor/plugins/smiley/images/regular_smile.gif" publishTime="09/21/2010 16:52:06" />
    <file relUrl="ckfinder/core/help/pl/files/other/help.js" publishTime="01/06/2010 13:32:16" />
    <file relUrl="Admin/Admin_Main.aspx" publishTime="09/10/2010 16:12:30" />
    <file relUrl="ckeditor/skins/office2003/images/noimage.png" publishTime="09/21/2010 16:52:06" />
    <file relUrl="ckfinder/core/help/es-mx/files/other/help.css" publishTime="01/04/2010 13:39:26" />
    <file relUrl="bin/Eisp.Entity.dll" publishTime="02/25/2013 23:22:24" />
    <file relUrl="Admin/Images/crm_19.gif" publishTime="08/18/2008 20:12:44" />
    <file relUrl="ckfinder/core/help/en/files/images/010.gif" publishTime="01/11/2010 14:32:32" />
    <file relUrl="ckfinder/core/help/en/files/images/016.gif" publishTime="01/11/2010 14:32:32" />
    <file relUrl="ckfinder/core/connector/aspx/lang/zh-cn.xml" publishTime="01/06/2010 10:28:00" />
    <file relUrl="ckfinder/core/pages/ckffolders.html" publishTime="01/11/2010 12:31:56" />
    <file relUrl="ckfinder/core/help/en/index.html" publishTime="01/04/2010 13:39:24" />
    <file relUrl="ckeditor/plugins/uicolor/yui/assets/hue_thumb.png" publishTime="09/21/2010 16:52:06" />
    <file relUrl="ckfinder/core/skins/silver/fck_editor.css" publishTime="01/04/2010 13:39:22" />
    <file relUrl="Images/firstg.gif" publishTime="04/30/2003 15:13:46" />
    <file relUrl="bin/zh-CHT/AspNetPager.resources.dll" publishTime="02/25/2013 23:22:26" />
    <file relUrl="ckfinder/core/help/en/files/011.html" publishTime="01/06/2010 13:32:18" />
    <file relUrl="ckeditor/ckeditor_basic.js" publishTime="09/21/2010 16:52:06" />
    <file relUrl="ckfinder/core/help/pl/files/images/009.png" publishTime="01/11/2010 14:32:34" />
    <file relUrl="ckeditor/lang/en.js" publishTime="09/21/2010 16:52:06" />
    <file relUrl="Images/ProductPhoto.jpg" publishTime="07/06/2009 11:35:32" />
    <file relUrl="ckeditor/ckeditor_source.js" publishTime="09/21/2010 16:52:06" />
    <file relUrl="ckfinder/core/help/en/files/006.html" publishTime="01/04/2010 13:39:24" />
    <file relUrl="ckeditor/skins/kama/templates.css" publishTime="09/21/2010 16:52:06" />
    <file relUrl="ckfinder/core/help/pl/files/009.html" publishTime="01/04/2010 13:39:30" />
    <file relUrl="ckfinder/core/help/en/files/008.html" publishTime="01/04/2010 13:39:24" />
    <file relUrl="Template/default/cn/controls/ContactBox.ascx" publishTime="10/14/2010 11:29:05" />
    <file relUrl="ckfinder/core/lang/fr.js" publishTime="01/06/2010 13:32:18" />
    <file relUrl="Template/default/cn/images/au_main.jpg" publishTime="10/13/2010 21:26:40" />
    <file relUrl="ckfinder/core/help/es-mx/files/003.html" publishTime="01/04/2010 13:39:28" />
    <file relUrl="ckfinder/core/connector/aspx/lang/nl.xml" publishTime="01/06/2010 10:27:58" />
    <file relUrl="ckeditor/skins/v2/dialog.css" publishTime="09/21/2010 16:52:06" />
    <file relUrl="Admin/Images/crm_23.gif" publishTime="08/18/2008 20:12:46" />
    <file relUrl="ckeditor/plugins/clipboard/dialogs/paste.js" publishTime="09/21/2010 16:52:06" />
    <file relUrl="ckfinder/core/help/pl/files/008.html" publishTime="01/04/2010 13:39:30" />
    <file relUrl="ckeditor/skins/v2/images/sprites.png" publishTime="09/21/2010 16:52:06" />
    <file relUrl="ckeditor/plugins/showblocks/images/block_h1.png" publishTime="09/21/2010 16:52:06" />
    <file relUrl="ckeditor/plugins/smiley/images/kiss.gif" publishTime="09/21/2010 16:52:06" />
    <file relUrl="ckeditor/skins/kama/images/sprites.png" publishTime="09/21/2010 16:52:06" />
    <file relUrl="ckfinder/core/images/icons/16/jpg.gif" publishTime="01/11/2010 14:32:34" />
    <file relUrl="Template/default/en/Css/ProductList.css" publishTime="10/24/2010 21:09:27" />
    <file relUrl="ckfinder/core/help/pl/files/001.html" publishTime="01/04/2010 13:39:30" />
    <file relUrl="Template/default/cn/Index.Master" publishTime="10/15/2010 21:18:04" />
    <file relUrl="bin/AspNetPager.pdb" publishTime="02/25/2013 23:22:25" />
    <file relUrl="Images/5r.gif" publishTime="04/24/2003 11:52:08" />
    <file relUrl="ckeditor/plugins/showblocks/images/block_h4.png" publishTime="09/21/2010 16:52:06" />
    <file relUrl="Images/4r.gif" publishTime="04/24/2003 11:51:30" />
    <file relUrl="ckfinder/core/help/en/files/suggestions.html" publishTime="01/04/2010 13:39:24" />
    <file relUrl="Admin/User/Admin.aspx" publishTime="09/20/2010 23:31:48" />
    <file relUrl="ckfinder/core/images/icons/32/jpg.gif" publishTime="01/11/2010 14:32:34" />
    <file relUrl="ckfinder/core/help/pl/files/toc.html" publishTime="01/04/2010 13:39:30" />
    <file relUrl="Admin/Images/Admin_Default/admin_title_bg_hide.gif" publishTime="12/08/2005 15:23:44" />
    <file relUrl="ProductDetail.aspx" publishTime="10/10/2010 16:24:47" />
    <file relUrl="ckeditor/plugins/smiley/images/envelope.gif" publishTime="09/21/2010 16:52:06" />
    <file relUrl="bin/eisp_basepage.pdb" publishTime="02/25/2013 23:22:27" />
    <file relUrl="ckfinder/core/help/pl/files/images/012.png" publishTime="01/11/2010 14:32:34" />
    <file relUrl="Template/default/cn/Guestbook.Master" publishTime="10/18/2010 16:18:09" />
    <file relUrl="ckfinder/core/images/icons/32/gif.gif" publishTime="01/11/2010 14:32:34" />
    <file relUrl="ckfinder/core/skins/office2003/images/toolbar.separator.gif" publishTime="01/11/2010 14:32:34" />
    <file relUrl="ckfinder/core/help/es/files/004.html" publishTime="01/04/2010 13:39:26" />
    <file relUrl="ckfinder/core/skins/silver/images/toolbar.arrowright.gif" publishTime="01/11/2010 14:32:34" />
    <file relUrl="ckfinder/core/help/es/files/images/020.png" publishTime="01/11/2010 14:32:32" />
    <file relUrl="ckfinder/core/help/en/files/images/013.gif" publishTime="01/11/2010 14:32:32" />
    <file relUrl="ckfinder/core/images/icons/32/pdf.gif" publishTime="01/11/2010 14:32:34" />
    <file relUrl="Template/default/cn/Profile.Master" publishTime="10/08/2010 23:16:35" />
    <file relUrl="ckeditor/plugins/showblocks/images/block_h2.png" publishTime="09/21/2010 16:52:06" />
    <file relUrl="ckfinder/core/help/pl/files/images/010.png" publishTime="01/11/2010 14:32:34" />
    <file relUrl="ckfinder/core/images/icons/32/fla.gif" publishTime="01/11/2010 14:32:34" />
    <file relUrl="ckfinder/core/help/es-mx/files/images/007.png" publishTime="01/11/2010 14:32:32" />
    <file relUrl="Admin/Images/crm_12.gif" publishTime="08/18/2008 20:12:44" />
    <file relUrl="OrderDetail.aspx" publishTime="10/14/2010 17:07:49" />
    <file relUrl="Downloads.aspx" publishTime="10/11/2010 16:11:36" />
    <file relUrl="ckfinder/core/skins/office2003/fck_editor.css" publishTime="01/04/2010 13:39:22" />
    <file relUrl="Admin/Downloads/DownloadAdmin.aspx" publishTime="10/10/2010 16:36:25" />
    <file relUrl="Template/default/cn/controls/Category.ascx" publishTime="10/09/2010 20:49:58" />
    <file relUrl="ckfinder/core/lang/pl.js" publishTime="01/06/2010 13:32:16" />
    <file relUrl="Admin/Images/Admin_Default/admin_top.gif" publishTime="09/10/2010 14:25:26" />
    <file relUrl="ckeditor/skins/kama/dialog.css" publishTime="09/21/2010 16:52:06" />
    <file relUrl="ckeditor/plugins/smiley/images/cry_smile.gif" publishTime="09/21/2010 16:52:06" />
    <file relUrl="Admin/Images/Admin_Default/admin_title.gif" publishTime="09/10/2010 14:09:45" />
    <file relUrl="Admin/Images/Admin_Default/admin_top_icon_2.gif" publishTime="04/05/2003 14:36:14" />
    <file relUrl="ckfinder/core/connector/aspx/lang/sl.xml" publishTime="01/06/2010 11:44:52" />
    <file relUrl="Admin/Images/crm_2.gif" publishTime="08/18/2008 20:12:42" />
    <file relUrl="ckeditor/plugins/scayt/dialogs/options.js" publishTime="09/21/2010 16:52:06" />
    <file relUrl="ckfinder/core/help/es-mx/files/images/014.gif" publishTime="01/11/2010 14:32:34" />
    <file relUrl="ckeditor/plugins/uicolor/uicolor.gif" publishTime="09/21/2010 16:52:06" />
    <file relUrl="ckeditor/config.js" publishTime="10/14/2010 12:12:21" />
    <file relUrl="ckfinder/core/help/en/files/images/001.gif" publishTime="01/11/2010 14:32:32" />
    <file relUrl="ckfinder/core/lang/nl.js" publishTime="01/06/2010 13:32:18" />
    <file relUrl="ckfinder/core/images/icons/32/cs.gif" publishTime="01/11/2010 14:32:34" />
    <file relUrl="ckeditor/skins/kama/images/mini.gif" publishTime="09/21/2010 16:52:06" />
    <file relUrl="ckfinder/core/lang/sk.js" publishTime="01/06/2010 13:32:18" />
    <file relUrl="ckfinder/core/connector/aspx/lang/da.xml" publishTime="01/06/2010 10:27:58" />
    <file relUrl="bin/Eisp.Entity.pdb" publishTime="02/25/2013 23:22:24" />
    <file relUrl="ckeditor/plugins/smiley/images/teeth_smile.gif" publishTime="09/21/2010 16:52:06" />
    <file relUrl="Template/default/cn/Css/Css.css" publishTime="10/15/2010 11:54:04" />
    <file relUrl="Admin/Products/ProductADD.aspx" publishTime="10/14/2010 15:30:48" />
    <file relUrl="ckfinder/core/skins/office2003/images/toolbar.start.gif" publishTime="01/11/2010 14:32:34" />
    <file relUrl="ckeditor/plugins/templates/templates/images/template1.gif" publishTime="09/21/2010 16:52:06" />
    <file relUrl="ckeditor/plugins/scayt/dialogs/toolbar.css" publishTime="09/21/2010 16:52:06" />
    <file relUrl="Admin/Images/crm_9.gif" publishTime="08/18/2008 20:12:42" />
    <file relUrl="ckeditor/skins/kama/icons.png" publishTime="09/21/2010 16:52:06" />
    <file relUrl="Template/default/cn/Order.Master" publishTime="10/14/2010 17:05:04" />
    <file relUrl="ckfinder/core/skins/office2003/images/toolbar.arrowright.gif" publishTime="01/11/2010 14:32:34" />
    <file relUrl="Admin/About/About.aspx" publishTime="10/14/2010 11:40:07" />
    <file relUrl="Admin/Images/Admin_Default/lock.gif" publishTime="02/18/2005 01:50:06" />
    <file relUrl="ckeditor/LICENSE.html" publishTime="09/21/2010 16:52:06" />
    <file relUrl="ckfinder/core/help/es/files/toc.html" publishTime="01/04/2010 13:39:26" />
    <file relUrl="ckfinder/core/help/es/files/images/013.png" publishTime="01/11/2010 14:32:32" />
    <file relUrl="ckeditor/plugins/templates/templates/default.js" publishTime="09/21/2010 16:52:06" />
    <file relUrl="ckfinder/core/help/en/files/images/017.gif" publishTime="01/11/2010 14:32:32" />
    <file relUrl="ckfinder/core/skins/default/fck_editor.css" publishTime="01/04/2010 13:39:22" />
    <file relUrl="ckfinder/core/help/en/files/images/007.gif" publishTime="01/11/2010 14:32:32" />
    <file relUrl="Images/moren.gif" publishTime="04/24/2003 17:01:26" />
    <file relUrl="ckfinder/core/images/icons/32/xls.gif" publishTime="01/11/2010 14:32:34" />
    <file relUrl="ckfinder/core/images/icons/16/pdf.gif" publishTime="01/11/2010 14:32:34" />
    <file relUrl="Template/default/cn/News.Master" publishTime="10/11/2010 16:11:02" />
    <file relUrl="Admin/Images/Admin_Default/admin_bulletin.gif" publishTime="05/20/2002 21:49:36" />
    <file relUrl="Admin/Images/crm_3.gif" publishTime="08/18/2008 20:12:42" />
    <file relUrl="ckfinder/core/help/es/files/011.html" publishTime="01/06/2010 13:35:24" />
    <file relUrl="ckfinder/core/skins/silver/fck_dialog.css" publishTime="01/04/2010 13:39:22" />
    <file relUrl="Template/default/en/Contact.Master" publishTime="10/15/2010 10:50:06" />
    <file relUrl="ckfinder/core/connector/aspx/connector.aspx" publishTime="01/06/2010 13:34:12" />
    <file relUrl="ckfinder/core/help/pl/files/images/015.gif" publishTime="01/11/2010 14:32:34" />
    <file relUrl="ckfinder/core/skins/silver/images/toolbar.end.gif" publishTime="01/11/2010 14:32:34" />
    <file relUrl="ckfinder/core/skins/office2003/images/toolbar.expand.gif" publishTime="01/11/2010 14:32:34" />
    <file relUrl="News.aspx" publishTime="10/11/2010 16:09:57" />
    <file relUrl="Admin/Products/productedit.aspx" publishTime="10/14/2010 16:00:15" />
    <file relUrl="ckfinder/core/help/en/files/images/014.gif" publishTime="01/11/2010 14:32:32" />
    <file relUrl="ckeditor/plugins/smiley/images/wink_smile.gif" publishTime="09/21/2010 16:52:06" />
    <file relUrl="ckfinder/core/help/en/files/004.html" publishTime="01/04/2010 13:39:24" />
    <file relUrl="Images/firstg1.gif" publishTime="04/24/2003 13:11:06" />
    <file relUrl="ckfinder/core/help/en/files/003.html" publishTime="01/04/2010 13:39:24" />
    <file relUrl="ckeditor/skins/office2003/templates.css" publishTime="09/21/2010 16:52:06" />
    <file relUrl="ckfinder/core/help/en/files/license.html" publishTime="01/04/2010 13:39:24" />
    <file relUrl="ckfinder/core/help/en/files/010.html" publishTime="01/04/2010 13:39:24" />
    <file relUrl="ckeditor/plugins/forms/dialogs/button.js" publishTime="09/21/2010 16:52:06" />
    <file relUrl="ckfinder/core/skins/silver/images/toolbar.buttonbg.gif" publishTime="01/11/2010 14:32:34" />
    <file relUrl="Template/default/en/images/au_menubg.jpg" publishTime="10/11/2010 16:00:35" />
    <file relUrl="Admin/Images/Admin_Default/admin_topic.gif" publishTime="02/26/2005 18:42:06" />
    <file relUrl="ckfinder/core/help/en/files/images/005.gif" publishTime="01/11/2010 14:32:32" />
    <file relUrl="ckfinder/core/help/es-mx/files/toc.html" publishTime="01/04/2010 13:39:28" />
    <file relUrl="ckfinder/core/images/icons/32/rdp.gif" publishTime="01/11/2010 14:32:34" />
    <file relUrl="Admin/Images/spacer.gif" publishTime="08/18/2008 20:12:44" />
    <file relUrl="GuestBook.aspx" publishTime="10/18/2010 13:52:39" />
    <file relUrl="Admin/Images/crm_5.gif" publishTime="08/18/2008 20:12:42" />
    <file relUrl="ckfinder/core/connector/aspx/lang/es.xml" publishTime="01/06/2010 10:27:58" />
    <file relUrl="ckfinder/core/lang/da.js" publishTime="01/06/2010 13:32:18" />
    <file relUrl="ckfinder/core/help/es-mx/files/images/013.png" publishTime="01/11/2010 14:32:32" />
    <file relUrl="Admin/Images/crm_21.gif" publishTime="08/18/2008 20:12:44" />
    <file relUrl="ckeditor/skins/kama/skin.js" publishTime="09/21/2010 16:52:06" />
    <file relUrl="Admin/News/NewsAdmin.aspx" publishTime="09/20/2010 17:46:15" />
    <file relUrl="bin/URLRewriter.dll" publishTime="07/17/2009 16:49:22" />
    <file relUrl="ckfinder/core/help/es-mx/files/images/002.gif" publishTime="01/11/2010 14:32:32" />
    <file relUrl="ckfinder/core/lang/zh-cn.js" publishTime="01/06/2010 13:32:16" />
    <file relUrl="ckeditor/plugins/templates/templates/images/template3.gif" publishTime="09/21/2010 16:52:06" />
    <file relUrl="ckfinder/core/connector/aspx/lang/it.xml" publishTime="01/06/2010 10:27:58" />
    <file relUrl="ckfinder/core/lang/lv.js" publishTime="01/06/2010 13:32:16" />
    <file relUrl="ckfinder/core/images/ckffolder.gif" publishTime="01/11/2010 14:32:34" />
    <file relUrl="ckfinder/core/images/toolbar/help.gif" publishTime="01/11/2010 14:32:34" />
    <file relUrl="install.txt" publishTime="03/12/2010 16:45:58" />
    <file relUrl="ckfinder/core/connector/aspx/lang/pl.xml" publishTime="01/06/2010 10:27:58" />
    <file relUrl="Admin/TopFrame.aspx" publishTime="09/11/2010 14:22:43" />
    <file relUrl="ckeditor/skins/office2003/images/dialog_sides.png" publishTime="09/21/2010 16:52:06" />
    <file relUrl="ckfinder/core/help/en/files/images/018.gif" publishTime="01/11/2010 14:32:32" />
    <file relUrl="ckfinder/core/help/es-mx/files/images/008.png" publishTime="01/11/2010 14:32:32" />
    <file relUrl="App_Data/eisp_data.mdb" publishTime="02/18/2013 16:46:37" />
    <file relUrl="ckfinder/core/help/es/files/012.html" publishTime="01/04/2010 13:39:26" />
    <file relUrl="ckeditor/plugins/flash/dialogs/flash.js" publishTime="09/21/2010 16:52:06" />
    <file relUrl="ckfinder/core/lang/cs.js" publishTime="01/06/2010 13:32:18" />
    <file relUrl="ckfinder/core/skins/silver/images/toolbar.collapse.gif" publishTime="01/11/2010 14:32:34" />
    <file relUrl="ckfinder/core/help/pl/files/images/018.gif" publishTime="01/11/2010 14:32:34" />
    <file relUrl="ckfinder/core/images/icons/16/xls.gif" publishTime="01/11/2010 14:32:34" />
    <file relUrl="Global.asax" publishTime="06/28/2010 18:35:43" />
    <file relUrl="ckfinder/core/pages/ckffiles.html" publishTime="01/11/2010 12:31:56" />
    <file relUrl="ckeditor/plugins/uicolor/yui/assets/yui.css" publishTime="09/21/2010 16:52:06" />
    <file relUrl="Admin/CheckCode.aspx" publishTime="02/17/2010 21:54:56" />
    <file relUrl="ckfinder/core/help/en/files/other/help.js" publishTime="01/06/2010 13:32:16" />
    <file relUrl="Profile.aspx" publishTime="09/29/2010 16:37:26" />
    <file relUrl="ckfinder/core/help/es/files/013.html" publishTime="01/04/2010 13:39:26" />
    <file relUrl="Images/5n.gif" publishTime="04/24/2003 11:51:58" />
    <file relUrl="ckfinder/core/connector/aspx/lang/de.xml" publishTime="01/06/2010 10:27:58" />
    <file relUrl="Admin/Images/newhead.css" publishTime="02/17/2010 21:53:33" />
    <file relUrl="ckeditor/skins/v2/templates.css" publishTime="09/21/2010 16:52:06" />
    <file relUrl="ckeditor/plugins/showblocks/images/block_h5.png" publishTime="09/21/2010 16:52:06" />
    <file relUrl="Admin/function.js" publishTime="03/22/2009 20:12:12" />
    <file relUrl="bin/Eisp.Common.pdb" publishTime="02/25/2013 23:22:24" />
    <file relUrl="ckfinder/core/images/icons/16/swf.gif" publishTime="01/11/2010 14:32:34" />
    <file relUrl="ckfinder/core/lang/sv.js" publishTime="01/06/2010 13:32:20" />
    <file relUrl="Template/default/cn/Css/ProductList.css" publishTime="10/18/2010 11:25:06" />
    <file relUrl="ckfinder/core/images/icons/16/dll.gif" publishTime="01/11/2010 14:32:34" />
    <file relUrl="bin/eisp_basepage.dll" publishTime="02/25/2013 23:22:27" />
    <file relUrl="ckeditor/plugins/link/images/anchor.gif" publishTime="09/21/2010 16:52:06" />
    <file relUrl="ckfinder/core/help/es-mx/files/012.html" publishTime="01/04/2010 13:39:28" />
    <file relUrl="ckfinder/core/connector/aspx/lang/es-mx.xml" publishTime="01/06/2010 10:27:58" />
    <file relUrl="Images/firstn.gif" publishTime="04/30/2003 15:13:24" />
    <file relUrl="JS/ChangeFontColor.js" publishTime="08/21/2009 16:45:14" />
    <file relUrl="ckfinder/core/help/en/files/images/006.gif" publishTime="01/11/2010 14:32:32" />
    <file relUrl="ckeditor/plugins/uicolor/yui/assets/picker_thumb.png" publishTime="09/21/2010 16:52:06" />
    <file relUrl="ckfinder/core/help/pl/files/images/006.png" publishTime="01/11/2010 14:32:34" />
    <file relUrl="Admin/Images/crm_16.gif" publishTime="08/18/2008 20:12:42" />
    <file relUrl="ckfinder/core/connector/aspx/lang/sk.xml" publishTime="01/06/2010 10:27:58" />
    <file relUrl="ckfinder/core/help/es/files/images/019.png" publishTime="01/11/2010 14:32:32" />
    <file relUrl="ckeditor/lang/zh.js" publishTime="09/21/2010 16:52:06" />
    <file relUrl="ckeditor/plugins/smiley/images/whatchutalkingabout_smile.gif" publishTime="09/21/2010 16:52:06" />
    <file relUrl="ckfinder/core/skins/silver/images/toolbar.expand.gif" publishTime="01/11/2010 14:32:34" />
    <file relUrl="ckfinder/core/help/pl/files/003.html" publishTime="01/04/2010 13:39:30" />
    <file relUrl="ckfinder/core/images/icons/16/cs.gif" publishTime="01/11/2010 14:32:34" />
    <file relUrl="ckfinder/core/images/icons/16/bmp.gif" publishTime="01/11/2010 14:32:34" />
    <file relUrl="ckfinder/core/help/es/files/images/017.gif" publishTime="01/11/2010 14:32:32" />
    <file relUrl="ckfinder/core/help/pl/files/006.html" publishTime="01/04/2010 13:39:30" />
    <file relUrl="ckfinder/core/images/icons/32/swf.gif" publishTime="01/11/2010 14:32:34" />
    <file relUrl="Template/default/cn/Product.Master" publishTime="10/10/2010 15:49:52" />
    <file relUrl="bin/Eisp.Web.pdb" publishTime="02/25/2013 23:22:28" />
    <file relUrl="ckfinder/core/help/es/files/001.html" publishTime="01/04/2010 13:39:26" />
    <file relUrl="ckfinder/core/help/pl/index.html" publishTime="01/04/2010 13:39:30" />
    <file relUrl="ckfinder/core/help/pl/files/other/help.css" publishTime="01/04/2010 13:39:28" />
    <file relUrl="ckfinder/core/lang/de.js" publishTime="01/06/2010 13:32:16" />
    <file relUrl="ckeditor/plugins/wsc/dialogs/wsc.css" publishTime="09/21/2010 16:52:06" />
    <file relUrl="ckfinder/core/help/es-mx/files/images/019.png" publishTime="01/11/2010 14:32:34" />
    <file relUrl="ckfinder/core/help/es/files/009.html" publishTime="01/04/2010 13:39:26" />
    <file relUrl="ckeditor/skins/kama/editor.css" publishTime="09/21/2010 16:52:06" />
    <file relUrl="ckfinder/core/lang/zh-tw.js" publishTime="01/06/2010 13:32:20" />
    <file relUrl="ckfinder/core/help/pl/files/images/013.png" publishTime="01/11/2010 14:32:34" />
    <file relUrl="ckfinder/core/help/es-mx/files/images/004.png" publishTime="01/11/2010 14:32:32" />
    <file relUrl="ckfinder/core/help/es-mx/files/header.html" publishTime="01/04/2010 13:39:28" />
    <file relUrl="Admin/Images/crm_10.gif" publishTime="08/18/2008 20:12:42" />
    <file relUrl="ckeditor/plugins/smiley/images/angry_smile.gif" publishTime="09/21/2010 16:52:06" />
    <file relUrl="Admin/Images/crm_20.gif" publishTime="08/18/2008 20:12:44" />
    <file relUrl="ckeditor/skins/office2003/images/dialog_sides.gif" publishTime="09/21/2010 16:52:06" />
    <file relUrl="Images/go.jpg" publishTime="09/01/2008 22:51:54" />
    <file relUrl="Images/9r.gif" publishTime="04/24/2003 11:55:48" />
    <file relUrl="ckfinder/core/images/icons/32/doc.gif" publishTime="01/11/2010 14:32:34" />
    <file relUrl="Images/8r.gif" publishTime="04/24/2003 11:55:10" />
    <file relUrl="ckeditor/ckeditor.js" publishTime="10/13/2010 23:08:20" />
    <file relUrl="Template/default/cn/Downloads.Master" publishTime="10/11/2010 16:12:17" />
    <file relUrl="Admin/Images/Admin_Default/admin_help.gif" publishTime="09/22/2004 13:39:58" />
    <file relUrl="Images/PDF.gif" publishTime="07/06/2009 13:49:48" />
    <file relUrl="ckfinder/core/help/es-mx/files/007.html" publishTime="01/04/2010 13:39:28" />
    <file relUrl="ckfinder/core/images/icons/32/default.icon.gif" publishTime="01/11/2010 14:32:34" />
    <file relUrl="Admin/Images/Admin_Default/admin_title_bg_show.gif" publishTime="12/08/2005 15:30:12" />
    <file relUrl="ckeditor/plugins/uicolor/lang/en.js" publishTime="09/21/2010 16:52:06" />
    <file relUrl="Admin/Images/Admin_Default/admin_top_icon_5.gif" publishTime="04/06/2003 11:30:24" />
    <file relUrl="ckfinder/core/images/icons/16/mp3.gif" publishTime="01/11/2010 14:32:34" />
    <file relUrl="Admin/Images/Admin_Default/admin_top_bg.gif" publishTime="09/10/2010 14:26:33" />
    <file relUrl="Admin/Images/Admin_Default/SortEnd_Folder_Close.gif" publishTime="05/16/2009 11:12:38" />
    <file relUrl="ckeditor/plugins/tabletools/dialogs/tableCell.js" publishTime="09/21/2010 16:52:06" />
    <file relUrl="bin/Eisp.BLL.pdb" publishTime="02/25/2013 23:22:27" />
    <file relUrl="ckfinder/core/help/es/files/other/help.css" publishTime="01/04/2010 13:39:26" />
    <file relUrl="ckfinder/core/images/icons/32/swt.gif" publishTime="01/11/2010 14:32:34" />
    <file relUrl="Images/1r.gif" publishTime="04/24/2003 11:41:24" />
    <file relUrl="ckfinder/core/help/es-mx/files/images/012.png" publishTime="01/11/2010 14:32:32" />
    <file relUrl="ckeditor/plugins/colordialog/dialogs/colordialog.js" publishTime="09/21/2010 16:52:06" />
    <file relUrl="Images/0r.gif" publishTime="04/24/2003 11:47:28" />
    <file relUrl="ckfinder/core/help/es-mx/files/images/011.png" publishTime="01/11/2010 14:32:32" />
    <file relUrl="ckeditor/plugins/smiley/images/omg_smile.gif" publishTime="09/21/2010 16:52:06" />
    <file relUrl="ckeditor/plugins/showblocks/images/block_address.png" publishTime="09/21/2010 16:52:06" />
    <file relUrl="ckfinder/core/help/es/files/header.html" publishTime="01/04/2010 13:39:26" />
    <file relUrl="ckeditor/images/spacer.gif" publishTime="09/21/2010 16:52:06" />
    <file relUrl="ckfinder/core/help/es/files/003.html" publishTime="01/04/2010 13:39:26" />
    <file relUrl="Contact.aspx" publishTime="10/11/2010 16:17:35" />
    <file relUrl="ckfinder/core/images/icons/32/vsd.gif" publishTime="01/11/2010 14:32:34" />
    <file relUrl="Admin/Images/crm_8.gif" publishTime="08/18/2008 20:12:46" />
    <file relUrl="ckfinder/core/help/pl/files/004.html" publishTime="01/04/2010 13:39:30" />
    <file relUrl="ckfinder/core/skins/default/images/toolbar.buttonarrow.gif" publishTime="01/11/2010 14:32:34" />
    <file relUrl="Admin/Images/Admin_Default/admin_top_icon_4.gif" publishTime="04/05/2003 14:36:30" />
    <file relUrl="ckfinder/core/help/en/files/images/019.gif" publishTime="01/11/2010 14:32:32" />
    <file relUrl="Admin/Images/Admin_Default/admin_top_icon_3.gif" publishTime="04/30/2003 17:07:16" />
    <file relUrl="ckfinder/core/help/es-mx/files/license.html" publishTime="01/04/2010 13:39:28" />
    <file relUrl="Admin/Index.aspx" publishTime="09/11/2010 13:58:45" />
    <file relUrl="ckeditor/plugins/smiley/images/devil_smile.gif" publishTime="09/21/2010 16:52:06" />
    <file relUrl="ckfinder/core/skins/office2003/images/toolbar.buttonarrow.gif" publishTime="01/11/2010 14:32:34" />
    <file relUrl="ckfinder/core/images/ckffolderopened.gif" publishTime="01/11/2010 14:32:34" />
    <file relUrl="Admin/Images/Admin_Default/admin_top_icon_1.gif" publishTime="04/05/2003 14:33:26" />
    <file relUrl="ckeditor/plugins/table/dialogs/table.js" publishTime="09/21/2010 16:52:06" />
    <file relUrl="ProductList.aspx" publishTime="10/10/2010 15:42:47" />
    <file relUrl="ckfinder/core/help/en/files/header.html" publishTime="01/04/2010 13:39:24" />
    <file relUrl="Index.aspx" publishTime="09/29/2010 16:55:09" />
    <file relUrl="ckfinder/core/help/en/files/007.html" publishTime="01/04/2010 13:39:24" />
    <file relUrl="ckfinder/core/skins/default/images/toolbar.separator.gif" publishTime="01/11/2010 14:32:34" />
    <file relUrl="bin/CKFinder.dll" publishTime="01/11/2010 14:32:34" />
    <file relUrl="ckeditor/skins/kama/images/dialog_sides_rtl.png" publishTime="09/21/2010 16:52:06" />
    <file relUrl="ckfinder/core/help/en/files/images/020.gif" publishTime="01/11/2010 14:32:32" />
    <file relUrl="Template/default/cn/controls/FooterBox.ascx" publishTime="10/10/2010 12:02:14" />
    <file relUrl="ckeditor/skins/v2/editor.css" publishTime="09/21/2010 16:52:06" />
    <file relUrl="Images/1n.gif" publishTime="04/24/2003 11:40:22" />
    <file relUrl="ckfinder/core/help/en/files/images/002.gif" publishTime="01/11/2010 14:32:32" />
    <file relUrl="ckfinder/core/help/es/files/images/016.gif" publishTime="01/11/2010 14:32:32" />
    <file relUrl="ckfinder/core/lang/es.js" publishTime="01/06/2010 13:32:20" />
    <file relUrl="ckfinder/config.ascx" publishTime="10/14/2010 13:40:30" />
    <file relUrl="Template/default/en/controls/DownloadBox.ascx" publishTime="10/24/2010 21:57:51" />
    <file relUrl="ckeditor/plugins/showblocks/images/block_p.png" publishTime="09/21/2010 16:52:06" />
    <file relUrl="Images/9n.gif" publishTime="04/24/2003 11:55:38" />
    <file relUrl="Images/firstn1.gif" publishTime="01/16/2003 13:22:24" />
    <file relUrl="ckeditor/plugins/div/dialogs/div.js" publishTime="09/21/2010 16:52:06" />
    <file relUrl="Images/8n.gif" publishTime="04/24/2003 11:54:44" />
    <file relUrl="ckfinder/core/images/icons/32/js.gif" publishTime="01/11/2010 14:32:34" />
    <file relUrl="App_Data/eisp_data.ascx" publishTime="02/19/2010 20:50:15" />
    <file relUrl="Images/6n.gif" publishTime="04/24/2003 11:52:56" />
    <file relUrl="ckeditor/plugins/templates/templates/images/template2.gif" publishTime="09/21/2010 16:52:06" />
    <file relUrl="Template/default/en/Css/Css.css" publishTime="10/24/2010 21:09:27" />
    <file relUrl="ckeditor/plugins/showblocks/images/block_h6.png" publishTime="09/21/2010 16:52:06" />
    <file relUrl="ckfinder/core/help/en/files/toc.html" publishTime="01/04/2010 13:39:24" />
    <file relUrl="Admin/Images/Admin_Default/article_pass.gif" publishTime="10/30/2002 14:12:26" />
    <file relUrl="ckeditor/plugins/smiley/images/angel_smile.gif" publishTime="09/21/2010 16:52:06" />
    <file relUrl="ckfinder/core/help/pl/files/005.html" publishTime="01/04/2010 13:39:30" />
    <file relUrl="ckeditor/plugins/dialog/dialogDefinition.js" publishTime="09/21/2010 16:52:06" />
    <file relUrl="ckeditor/plugins/smiley/images/embaressed_smile.gif" publishTime="09/21/2010 16:52:06" />
    <file relUrl="ckeditor/plugins/uicolor/yui/assets/hue_bg.png" publishTime="09/21/2010 16:52:06" />
    <file relUrl="ckfinder/core/help/es-mx/files/images/017.gif" publishTime="01/11/2010 14:32:34" />
    <file relUrl="Admin/Images/Admin_Default/admin_key.gif" publishTime="06/06/2004 14:55:18" />
    <file relUrl="Template/default/en/Order.Master" publishTime="10/15/2010 10:51:52" />
    <file relUrl="ckfinder/core/help/en/files/images/004.gif" publishTime="01/11/2010 14:32:32" />
    <file relUrl="Admin/Admin_UpFile.aspx" publishTime="02/21/2010 22:10:27" />
    <file relUrl="ckfinder/core/help/pl/files/011.html" publishTime="01/06/2010 13:32:18" />
    <file relUrl="ckfinder/core/help/en/files/images/015.gif" publishTime="01/11/2010 14:32:32" />
    <file relUrl="NewsDetail.aspx" publishTime="10/15/2010 10:44:29" />
    <file relUrl="Admin/Images/Admin_Default/Sort_File_End.gif" publishTime="05/16/2009 11:12:40" />
    <file relUrl="ckfinder/core/images/toolbar/download.gif" publishTime="01/11/2010 14:32:34" />
    <file relUrl="ckfinder/core/connector/aspx/lang/el.xml" publishTime="01/06/2010 11:43:32" />
    <file relUrl="ckfinder/core/help/es-mx/files/008.html" publishTime="01/04/2010 13:39:28" />
    <file relUrl="ckfinder/Web.config" publishTime="10/14/2010 13:50:24" />
    <file relUrl="ckeditor/plugins/forms/dialogs/textarea.js" publishTime="09/21/2010 16:52:06" />
    <file relUrl="ckfinder/core/skins/default/images/toolbar.start.gif" publishTime="01/11/2010 14:32:34" />
    <file relUrl="Images/0n.gif" publishTime="04/24/2003 11:46:48" />
    <file relUrl="Images/lastg2.gif" publishTime="04/24/2003 13:11:38" />
    <file relUrl="Admin/Images/Admin_Default/Sort_Listline.gif" publishTime="05/16/2009 11:12:40" />
    <file relUrl="ckeditor/plugins/wsc/dialogs/tmpFrameset.html" publishTime="09/21/2010 16:52:06" />
    <file relUrl="ckfinder/core/help/es-mx/files/images/003.gif" publishTime="01/11/2010 14:32:32" />
    <file relUrl="Admin/Images/crm_11.gif" publishTime="08/18/2008 20:12:42" />
    <file relUrl="ckfinder/core/help/pl/files/images/004.png" publishTime="01/11/2010 14:32:34" />
    <file relUrl="ckfinder/core/help/es/files/010.html" publishTime="01/04/2010 13:39:26" />
    <file relUrl="ckfinder/core/lang/it.js" publishTime="01/06/2010 13:32:16" />
    <file relUrl="ckfinder/core/help/pl/files/images/014.gif" publishTime="01/11/2010 14:32:34" />
    <file relUrl="ckeditor/plugins/smiley/images/lightbulb.gif" publishTime="09/21/2010 16:52:06" />
    <file relUrl="ckfinder/core/help/pl/files/images/020.png" publishTime="01/11/2010 14:32:34" />
    <file relUrl="ckeditor/contents.css" publishTime="09/21/2010 16:52:06" />
    <file relUrl="ckeditor/skins/office2003/skin.js" publishTime="09/21/2010 16:52:06" />
    <file relUrl="Styles/admin_Default.css" publishTime="09/20/2010 17:26:13" />
    <file relUrl="Images/7r.gif" publishTime="04/24/2003 11:53:58" />
    <file relUrl="ckeditor/plugins/about/dialogs/logo_ckeditor.png" publishTime="09/21/2010 16:52:06" />
    <file relUrl="Admin/Images/crm_4.gif" publishTime="08/18/2008 20:12:42" />
    <file relUrl="Template/default/cn/controls/ProductBox.ascx" publishTime="10/15/2010 21:22:28" />
    <file relUrl="Admin/Images/Admin_Default/lframe_t.gif" publishTime="12/08/2005 15:54:16" />
    <file relUrl="Admin/News/NewsClassAdmin.aspx" publishTime="09/21/2010 12:58:18" />
    <file relUrl="ckeditor/plugins/specialchar/dialogs/specialchar.js" publishTime="09/21/2010 16:52:06" />
    <file relUrl="ckfinder/core/skins/office2003/images/toolbar.end.gif" publishTime="01/11/2010 14:32:34" />
    <file relUrl="ckfinder/core/help/pl/files/images/016.gif" publishTime="01/11/2010 14:32:34" />
    <file relUrl="ckfinder/core/lang/en.js" publishTime="01/07/2010 19:51:28" />
    <file relUrl="ckfinder/core/help/es-mx/files/images/005.png" publishTime="01/11/2010 14:32:32" />
    <file relUrl="Template/default/en/Index.Master" publishTime="10/24/2010 21:08:20" />
    <file relUrl="ckfinder/core/help/es-mx/files/009.html" publishTime="01/04/2010 13:39:28" />
    <file relUrl="ckfinder/core/help/es-mx/files/004.html" publishTime="01/04/2010 13:39:28" />
    <file relUrl="ckfinder/core/help/en/files/images/008.gif" publishTime="01/11/2010 14:32:32" />
    <file relUrl="ckeditor/skins/v2/images/sprites_ie6.png" publishTime="09/21/2010 16:52:06" />
    <file relUrl="ckfinder/core/help/es/files/002.html" publishTime="01/04/2010 13:39:26" />
    <file relUrl="ckeditor/plugins/smiley/images/thumbs_up.gif" publishTime="09/21/2010 16:52:06" />
    <file relUrl="ckeditor/plugins/uicolor/plugin.js" publishTime="09/21/2010 16:52:06" />
    <file relUrl="ckeditor/plugins/smiley/images/sad_smile.gif" publishTime="09/21/2010 16:52:06" />
    <file relUrl="ckeditor/skins/v2/images/mini.gif" publishTime="09/21/2010 16:52:06" />
    <file relUrl="ckfinder/core/help/en/files/other/help.css" publishTime="01/04/2010 13:39:24" />
    <file relUrl="Images/6r.gif" publishTime="04/24/2003 11:53:22" />
    <file relUrl="ckeditor/plugins/smiley/images/tounge_smile.gif" publishTime="09/21/2010 16:52:06" />
    <file relUrl="ckfinder/core/images/ckfplus.gif" publishTime="01/11/2010 14:32:34" />
    <file relUrl="ckfinder/core/help/es/files/suggestions.html" publishTime="01/04/2010 13:39:26" />
    <file relUrl="ckeditor/plugins/uicolor/yui/assets/picker_mask.png" publishTime="09/21/2010 16:52:06" />
    <file relUrl="ckfinder/core/help/es-mx/files/other/help.js" publishTime="01/06/2010 13:32:16" />
    <file relUrl="ckfinder/core/images/toolbar/add.gif" publishTime="01/11/2010 14:32:34" />
    <file relUrl="Admin/Images/Admin_Default/Sort_File.gif" publishTime="05/16/2009 11:12:40" />
    <file relUrl="Images/nozzle2.jpg" publishTime="08/18/2009 11:44:04" />
    <file relUrl="ckfinder/core/images/spacer.gif" publishTime="01/11/2010 14:32:34" />
    <file relUrl="ckfinder/core/help/es-mx/files/005.html" publishTime="01/04/2010 13:39:28" />
    <file relUrl="ckfinder/core/help/en/files/images/012.gif" publishTime="01/11/2010 14:32:32" />
    <file relUrl="ckfinder/core/help/es-mx/files/010.html" publishTime="01/04/2010 13:39:28" />
    <file relUrl="Images/nextn.gif" publishTime="01/16/2003 16:12:32" />
    <file relUrl="Admin/Link/Admin_Link.aspx" publishTime="02/21/2010 22:10:26" />
    <file relUrl="ckeditor/INSTALL.html" publishTime="09/21/2010 16:52:06" />
    <file relUrl="ckfinder/core/images/icons/32/zip.gif" publishTime="01/11/2010 14:32:34" />
    <file relUrl="ckeditor/skins/kama/images/dialog_sides.gif" publishTime="09/21/2010 16:52:06" />
    <file relUrl="ckeditor/plugins/smiley/images/shades_smile.gif" publishTime="09/21/2010 16:52:06" />
    <file relUrl="ckfinder/core/images/icons/16/ppt.gif" publishTime="01/11/2010 14:32:34" />
    <file relUrl="ckfinder/core/help/es-mx/files/suggestions.html" publishTime="01/04/2010 13:39:28" />
    <file relUrl="ckeditor/plugins/image/dialogs/image.js" publishTime="09/21/2010 16:52:06" />
    <file relUrl="ckeditor/skins/office2003/dialog.css" publishTime="09/21/2010 16:52:06" />
    <file relUrl="ckfinder/core/connector/aspx/lang/sv.xml" publishTime="01/06/2010 10:27:58" />
    <file relUrl="Template/default/en/images/au_top.jpg" publishTime="10/11/2010 16:00:35" />
    <file relUrl="Template/default/en/ProductDetail.Master" publishTime="10/24/2010 21:13:07" />
    <file relUrl="ckfinder/core/help/pl/files/images/017.gif" publishTime="01/11/2010 14:32:34" />
    <file relUrl="ckfinder/core/skins/default/fck_dialog.css" publishTime="01/04/2010 13:39:22" />
    <file relUrl="Admin/Images/crm_7.gif" publishTime="08/18/2008 20:12:44" />
    <file relUrl="ckeditor/plugins/forms/dialogs/textfield.js" publishTime="09/21/2010 16:52:06" />
    <file relUrl="ckfinder/core/help/es-mx/files/006.html" publishTime="01/04/2010 13:39:28" />
    <file relUrl="Images/4n.gif" publishTime="04/24/2003 11:51:04" />
    <file relUrl="ckeditor/skins/v2/images/dialog_sides.gif" publishTime="09/21/2010 16:52:06" />
    <file relUrl="Template/default/en/Product.Master" publishTime="10/15/2010 10:53:31" />
    <file relUrl="Styles/leftFrame.css" publishTime="09/03/2007 02:10:06" />
    <file relUrl="Template/default/en/controls/HeaderBox.ascx" publishTime="10/24/2010 21:11:17" />
    <file relUrl="ckfinder/core/help/es/files/images/004.png" publishTime="01/11/2010 14:32:32" />
    <file relUrl="ckeditor/plugins/forms/dialogs/checkbox.js" publishTime="09/21/2010 16:52:06" />
    <file relUrl="ckfinder/core/help/es/files/license.html" publishTime="01/04/2010 13:39:26" />
    <file relUrl="Images/prevn.gif" publishTime="01/16/2003 13:23:44" />
    <file relUrl="ckfinder/core/help/en/files/005.html" publishTime="01/04/2010 13:39:24" />
    <file relUrl="ckeditor/skins/kama/images/noimage.png" publishTime="09/21/2010 16:52:06" />
    <file relUrl="ckfinder/core/help/en/files/002.html" publishTime="01/04/2010 13:39:24" />
    <file relUrl="ckfinder/core/images/icons/32/exe.gif" publishTime="01/11/2010 14:32:34" />
    <file relUrl="ckfinder/core/help/pl/files/images/008.png" publishTime="01/11/2010 14:32:34" />
    <file relUrl="ckeditor/plugins/templates/dialogs/templates.js" publishTime="09/21/2010 16:52:06" />
    <file relUrl="Template/default/cn/Contact.Master" publishTime="10/11/2010 16:18:22" />
    <file relUrl="ckeditor/plugins/forms/dialogs/radio.js" publishTime="09/21/2010 16:52:06" />
    <file relUrl="ckeditor/themes/default/theme.js" publishTime="09/21/2010 16:52:06" />
    <file relUrl="ckfinder/core/connector/aspx/lang/zh-tw.xml" publishTime="01/06/2010 10:28:00" />
    <file relUrl="ckfinder/core/help/es-mx/files/images/010.gif" publishTime="01/11/2010 14:32:32" />
    <file relUrl="Template/default/en/Guestbook.Master" publishTime="10/18/2010 16:21:41" />
    <file relUrl="ckeditor/adapters/jquery.js" publishTime="09/21/2010 16:52:06" />
    <file relUrl="ckeditor/lang/zh-cn.js" publishTime="09/21/2010 16:52:06" />
    <file relUrl="Admin/LogOut.aspx" publishTime="02/21/2010 22:10:26" />
    <file relUrl="ckfinder/core/help/es/files/images/014.gif" publishTime="01/11/2010 14:32:32" />
    <file relUrl="ckfinder/core/help/pl/files/images/011.png" publishTime="01/11/2010 14:32:34" />
    <file relUrl="ckfinder/core/help/pl/files/images/019.png" publishTime="01/11/2010 14:32:34" />
    <file relUrl="ckfinder/core/images/icons/16/js.gif" publishTime="01/11/2010 14:32:34" />
    <file relUrl="ckfinder/core/skins/silver/images/toolbar.separator.gif" publishTime="01/11/2010 14:32:34" />
    <file relUrl="ckfinder/core/images/icons/16/ai.gif" publishTime="01/11/2010 14:32:34" />
    <file relUrl="ckfinder/core/help/es/files/images/012.png" publishTime="01/11/2010 14:32:32" />
    <file relUrl="Admin/Images/Admin_Default/admin_img.gif" publishTime="05/20/2002 13:14:38" />
    <file relUrl="Images/2r.gif" publishTime="04/24/2003 11:48:22" />
    <file relUrl="ckfinder/core/help/pl/files/010.html" publishTime="01/04/2010 13:39:30" />
    <file relUrl="ckeditor/plugins/iframedialog/plugin.js" publishTime="09/21/2010 16:52:06" />
    <file relUrl="ckfinder/core/help/es-mx/files/013.html" publishTime="01/04/2010 13:39:28" />
    <file relUrl="ckeditor/skins/v2/skin.js" publishTime="09/21/2010 16:52:06" />
    <file relUrl="ckeditor/skins/office2003/images/sprites_ie6.png" publishTime="09/21/2010 16:52:06" />
    <file relUrl="ckfinder/core/help/en/files/images/009.gif" publishTime="01/11/2010 14:32:32" />
    <file relUrl="ckfinder/core/pages/blank.html" publishTime="01/06/2010 13:32:20" />
    <file relUrl="Admin/Images/Admin_Default/article_nopass.gif" publishTime="10/30/2002 14:20:30" />
    <file relUrl="ckfinder/core/images/icons/32/xml.gif" publishTime="01/11/2010 14:32:34" />
    <file relUrl="ckfinder/core/lang/es-mx.js" publishTime="01/06/2010 13:32:20" />
    <file relUrl="ckfinder/core/images/toolbar/settings.gif" publishTime="01/11/2010 14:32:34" />
    <file relUrl="ckfinder/core/help/en/files/012.html" publishTime="01/04/2010 13:39:24" />
    <file relUrl="Template/default/cn/ProductDetail.Master" publishTime="10/24/2010 21:12:24" />
    <file relUrl="ckfinder/core/lang/ru.js" publishTime="01/06/2010 13:32:16" />
    <file relUrl="Admin/Products/ProClassAdmin.aspx" publishTime="09/20/2010 17:39:11" />
    <file relUrl="Styles/topFrame.css" publishTime="09/10/2010 13:41:29" />
    <file relUrl="ckeditor/plugins/uicolor/dialogs/uicolor.js" publishTime="09/21/2010 16:52:06" />
    <file relUrl="ckfinder/core/lang/el.js" publishTime="01/06/2010 13:32:18" />
    <file relUrl="ckfinder/core/skins/default/images/toolbar.expand.gif" publishTime="01/11/2010 14:32:34" />
    <file relUrl="ckfinder/core/css/ckfinder.css" publishTime="01/06/2010 13:32:16" />
    <file relUrl="ckfinder/core/lang/pt-br.js" publishTime="01/06/2010 13:32:20" />
    <file relUrl="bin/Eisp.DAL.pdb" publishTime="02/25/2013 23:22:26" />
    <file relUrl="ckeditor/plugins/uicolor/yui/yui.js" publishTime="09/21/2010 16:52:06" />
    <file relUrl="Admin/Images/Admin_Default/Sort_Folder_Open.gif" publishTime="05/16/2009 11:12:40" />
    <file relUrl="Admin/Images/css1.css" publishTime="02/17/2010 21:53:33" />
    <file relUrl="ckfinder/core/help/es-mx/files/011.html" publishTime="01/06/2010 13:32:18" />
    <file relUrl="Template/default/en/images/au_main.jpg" publishTime="10/13/2010 21:26:35" />
    <file relUrl="ckfinder/core/skins/office2003/images/toolbar.collapse.gif" publishTime="01/11/2010 14:32:34" />
    <file relUrl="ckfinder/core/images/icons/32/ppt.gif" publishTime="01/11/2010 14:32:34" />
    <file relUrl="ckfinder/core/help/es/files/images/015.gif" publishTime="01/11/2010 14:32:32" />
    <file relUrl="ckfinder/core/skins/office2003/fck_dialog.css" publishTime="01/04/2010 13:39:22" />
    <file relUrl="Template/default/en/controls/FooterBox.ascx" publishTime="10/15/2010 10:49:25" />
    <file relUrl="ckeditor/skins/v2/images/toolbar_start.gif" publishTime="09/21/2010 16:52:06" />
    <file relUrl="Admin/Images/crm_13.gif" publishTime="08/18/2008 20:12:46" />
    <file relUrl="ckfinder/core/help/es/files/images/010.gif" publishTime="01/11/2010 14:32:32" />
    <file relUrl="Template/default/cn/images/au_menubg.jpg" publishTime="06/28/2010 22:13:29" />
    <file relUrl="bin/Eisp.BLL.dll" publishTime="02/25/2013 23:22:27" />
    <file relUrl="Template/default/cn/OrderDetail.Master" publishTime="10/18/2010 11:28:20" />
    <file relUrl="Admin/Images/crm_17.gif" publishTime="08/18/2008 20:12:42" />
    <file relUrl="ckfinder/core/images/icons/16/xml.gif" publishTime="01/11/2010 14:32:34" />
    <file relUrl="ckeditor/plugins/showblocks/images/block_div.png" publishTime="09/21/2010 16:52:06" />
    <file relUrl="Images/nextg.gif" publishTime="04/24/2003 13:12:22" />
    <file relUrl="ckfinder/core/images/icons/32/dll.gif" publishTime="01/11/2010 14:32:34" />
    <file relUrl="ckfinder/core/help/pl/files/images/001.jpg" publishTime="01/11/2010 14:32:34" />
    <file relUrl="ckfinder/core/help/es/files/images/003.gif" publishTime="01/11/2010 14:32:32" />
    <file relUrl="ckfinder/core/help/pl/files/images/002.gif" publishTime="01/11/2010 14:32:34" />
    <file relUrl="ckfinder/core/images/icons/32/bmp.gif" publishTime="01/11/2010 14:32:34" />
    <file relUrl="ckeditor/plugins/smiley/images/confused_smile.gif" publishTime="09/21/2010 16:52:06" />
    <file relUrl="ckeditor/skins/office2003/icons.png" publishTime="09/21/2010 16:52:06" />
    <file relUrl="Template/default/en/controls/NewsBox.ascx" publishTime="10/15/2010 10:49:46" />
    <file relUrl="Admin/SysLogin.aspx" publishTime="02/21/2010 22:10:22" />
    <file relUrl="ckeditor/plugins/pagebreak/images/pagebreak.gif" publishTime="09/21/2010 16:52:06" />
    <file relUrl="JS/Js.js" publishTime="07/20/2009 14:40:48" />
    <file relUrl="ckfinder/core/help/es-mx/index.html" publishTime="01/04/2010 13:39:28" />
    <file relUrl="Images/nozzle1.jpg" publishTime="07/06/2009 09:47:36" />
    <file relUrl="Images/7n.gif" publishTime="04/24/2003 11:53:42" />
    <file relUrl="ckfinder/core/help/en/files/images/003.gif" publishTime="01/11/2010 14:32:32" />
    <file relUrl="ckeditor/plugins/forms/dialogs/select.js" publishTime="09/21/2010 16:52:06" />
    <file relUrl="ckfinder/core/help/es-mx/files/images/006.png" publishTime="01/11/2010 14:32:32" />
    <file relUrl="ckfinder/core/help/es/files/005.html" publishTime="01/04/2010 13:39:26" />
    <file relUrl="ckeditor/plugins/smiley/images/thumbs_down.gif" publishTime="09/21/2010 16:52:06" />
    <file relUrl="ckeditor/plugins/wsc/dialogs/ciframe.html" publishTime="09/21/2010 16:52:06" />
    <file relUrl="ckeditor/plugins/link/dialogs/link.js" publishTime="09/21/2010 16:52:06" />
    <file relUrl="ckfinder/core/images/icons/32/avi.gif" publishTime="01/11/2010 14:32:34" />
    <file relUrl="ckfinder/core/help/es/files/other/help.js" publishTime="01/06/2010 13:32:16" />
    <file relUrl="Template/default/cn/controls/DownloadBox.ascx" publishTime="02/23/2010 10:43:17" />
    <file relUrl="ckfinder/core/js/ckfinder_ie.js" publishTime="03/12/2010 17:31:35" />
    <file relUrl="ckfinder/core/images/icons/16/default.icon.gif" publishTime="01/11/2010 14:32:34" />
    <file relUrl="ckeditor/plugins/pastetext/dialogs/pastetext.js" publishTime="09/21/2010 16:52:06" />
    <file relUrl="ckfinder/core/help/pl/files/013.html" publishTime="01/04/2010 13:39:30" />
    <file relUrl="bin/Eisp.Web.dll" publishTime="02/25/2013 23:22:28" />
    <file relUrl="ckeditor/plugins/showblocks/images/block_blockquote.png" publishTime="09/21/2010 16:52:06" />
    <file relUrl="Template/default/en/controls/Category.ascx" publishTime="10/09/2010 20:49:58" />
    <file relUrl="ckfinder/core/help/es/files/008.html" publishTime="01/04/2010 13:39:26" />
    <file relUrl="Images/lastg.gif" publishTime="04/30/2003 15:07:32" />
    <file relUrl="ckfinder/core/skins/default/images/toolbar.end.gif" publishTime="01/11/2010 14:32:34" />
    <file relUrl="ckfinder/core/images/icons/16/mdb.gif" publishTime="01/11/2010 14:32:34" />
    <file relUrl="ckeditor/skins/office2003/editor.css" publishTime="09/21/2010 16:52:06" />
    <file relUrl="ckfinder/core/help/pl/files/images/005.png" publishTime="01/11/2010 14:32:34" />
    <file relUrl="Admin/Images/crm_14.gif" publishTime="08/18/2008 20:12:42" />
    <file relUrl="ckfinder/core/images/toolbar/refresh.gif" publishTime="01/11/2010 14:32:34" />
    <file relUrl="ckfinder/core/help/es-mx/files/images/001.png" publishTime="01/11/2010 14:32:32" />
    <file relUrl="ckfinder/core/help/es-mx/files/001.html" publishTime="01/04/2010 13:39:28" />
    <file relUrl="Admin/Images/crm_24.gif" publishTime="08/18/2008 20:12:44" />
    <file relUrl="ckfinder/core/help/es-mx/files/images/009.png" publishTime="01/11/2010 14:32:32" />
    <file relUrl="Styles/default.css" publishTime="08/28/2007 23:31:30" />
    <file relUrl="ckfinder/core/connector/aspx/lang/pt-br.xml" publishTime="01/06/2010 10:27:58" />
    <file relUrl="Images/CategoryImages.gif" publishTime="07/06/2009 11:02:20" />
    <file relUrl="Template/default/cn/controls/NewsBox.ascx" publishTime="10/11/2010 16:07:01" />
    <file relUrl="Template/default/en/controls/ContactBox.ascx" publishTime="10/15/2010 10:48:59" />
    <file relUrl="ckfinder/core/images/ckfnothumb.gif" publishTime="01/11/2010 14:32:34" />
    <file relUrl="ckfinder/core/skins/office2003/images/toolbar.bg.gif" publishTime="01/11/2010 14:32:34" />
    <file relUrl="Admin/Images/crm_1.gif" publishTime="08/18/2008 20:12:42" />
    <file relUrl="Admin/Products/ProductAdmin.aspx" publishTime="10/18/2010 13:46:12" />
    <file relUrl="ckeditor/skins/v2/images/dialog_sides.png" publishTime="09/21/2010 16:52:06" />
    <file relUrl="ckeditor/plugins/smiley/images/broken_heart.gif" publishTime="09/21/2010 16:52:06" />
    <file relUrl="ckeditor/plugins/find/dialogs/find.js" publishTime="09/21/2010 16:52:06" />
    <file relUrl="ckfinder/core/skins/silver/images/toolbar.start.gif" publishTime="01/11/2010 14:32:34" />
    <file relUrl="ckfinder/core/help/pl/files/images/007.jpg" publishTime="01/11/2010 14:32:34" />
    <file relUrl="Admin/Images/crm_6.gif" publishTime="08/18/2008 20:12:42" />
    <file relUrl="ckfinder/core/images/icons/16/zip.gif" publishTime="01/11/2010 14:32:34" />
    <file relUrl="ckfinder/core/help/pl/files/012.html" publishTime="01/04/2010 13:39:30" />
    <file relUrl="ckfinder/core/help/es/files/images/009.png" publishTime="01/11/2010 14:32:32" />
    <file relUrl="ckfinder/core/help/es/files/images/005.png" publishTime="01/11/2010 14:32:32" />
    <file relUrl="Web.config" publishTime="02/25/2013 23:24:44" />
    <file relUrl="Images/2n.gif" publishTime="04/24/2003 11:48:08" />
    <file relUrl="ckfinder/ckfinder.html" publishTime="10/14/2010 13:44:32" />
    <file relUrl="Admin/Images/Admin_Default/Sort_Folder_Close.gif" publishTime="05/16/2009 11:12:40" />
    <file relUrl="Template/default/en/controls/ProductBox.ascx" publishTime="10/24/2010 21:26:56" />
    <file relUrl="ckfinder/core/help/pl/files/header.html" publishTime="01/04/2010 13:39:30" />
    <file relUrl="ckfinder/core/help/en/files/013.html" publishTime="01/04/2010 13:39:24" />
    <file relUrl="ckeditor/skins/v2/icons.png" publishTime="09/21/2010 16:52:06" />
    <file relUrl="ckfinder/core/help/es-mx/files/images/015.gif" publishTime="01/11/2010 14:32:34" />
    <file relUrl="ckfinder/core/help/pl/files/007.html" publishTime="01/04/2010 13:39:30" />
    <file relUrl="Admin/Images/crm_18.gif" publishTime="08/18/2008 20:12:44" />
    <file relUrl="Images/nozzle.jpg" publishTime="08/21/2009 17:47:56" />
    <file relUrl="ckfinder/core/help/es-mx/files/images/016.gif" publishTime="01/11/2010 14:32:34" />
    <file relUrl="ckfinder/core/help/es/files/images/007.png" publishTime="01/11/2010 14:32:32" />
    <file relUrl="ckfinder/core/help/es/files/images/008.png" publishTime="01/11/2010 14:32:32" />
    <file relUrl="ckeditor/plugins/showblocks/images/block_h3.png" publishTime="09/21/2010 16:52:06" />
    <file relUrl="Images/lastn2.gif" publishTime="01/16/2003 16:11:40" />
    <file relUrl="Template/default/cn/controls/HeaderBox.ascx" publishTime="10/10/2010 15:40:57" />
    <file relUrl="ckfinder/core/help/pl/files/license.html" publishTime="01/04/2010 13:39:30" />
    <file relUrl="ckeditor/plugins/showblocks/images/block_pre.png" publishTime="09/21/2010 16:52:06" />
    <file relUrl="Admin/News/NewsEdit.aspx" publishTime="10/10/2010 17:08:06" />
    <file relUrl="Admin/Guestbook/GuestBook.aspx" publishTime="09/20/2010 18:00:45" />
    <file relUrl="ckfinder/core/images/icons/32/ai.gif" publishTime="01/11/2010 14:32:34" />
    <file relUrl="ckfinder/core/connector/aspx/lang/en.xml" publishTime="01/06/2010 10:27:58" />
    <file relUrl="ckfinder/core/images/toolbar/delete.gif" publishTime="01/11/2010 14:32:34" />
    <file relUrl="ckfinder/core/lang/sl.js" publishTime="01/06/2010 13:32:18" />
    <file relUrl="bin/AspNetPager.dll" publishTime="02/25/2013 23:22:25" />
    <file relUrl="ckfinder/core/images/toolbar/view.gif" publishTime="01/11/2010 14:32:34" />
    <file relUrl="ckfinder/core/help/es-mx/files/images/018.png" publishTime="01/11/2010 14:32:34" />
    <file relUrl="ckeditor/skins/v2/images/dialog_sides_rtl.png" publishTime="09/21/2010 16:52:06" />
    <file relUrl="ckfinder/core/images/icons/16/swt.gif" publishTime="01/11/2010 14:32:34" />
    <file relUrl="ckfinder/core/skins/default/images/toolbar.arrowright.gif" publishTime="01/11/2010 14:32:34" />
    <file relUrl="ckfinder/core/help/pl/files/images/003.gif" publishTime="01/11/2010 14:32:34" />
    <file relUrl="Images/3r.gif" publishTime="04/24/2003 11:50:20" />
    <file relUrl="ckeditor/plugins/link/dialogs/anchor.js" publishTime="09/21/2010 16:52:06" />
    <file relUrl="Admin/News/NewsADD.aspx" publishTime="10/10/2010 17:09:02" />
    <file relUrl="ckfinder/core/images/icons/16/avi.gif" publishTime="01/11/2010 14:32:34" />
    <file relUrl="ckeditor/plugins/smiley/images/heart.gif" publishTime="09/21/2010 16:52:06" />
    <file relUrl="Template/default/en/Downloads.Master" publishTime="10/15/2010 10:50:19" />
    <file relUrl="ckfinder/core/help/es/files/images/006.png" publishTime="01/11/2010 14:32:32" />
    <file relUrl="ckfinder/core/skins/silver/images/toolbar.buttonarrow.gif" publishTime="01/11/2010 14:32:34" />
    <file relUrl="ckfinder/core/images/icons/16/txt.gif" publishTime="01/11/2010 14:32:34" />
    <file relUrl="ckeditor/skins/kama/images/sprites_ie6.png" publishTime="09/21/2010 16:52:06" />
    <file relUrl="Template/default/en/News.Master" publishTime="10/15/2010 10:51:27" />
    <file relUrl="ckeditor/plugins/pastefromword/filter/default.js" publishTime="09/21/2010 16:52:06" />
    <file relUrl="ckfinder/core/js/ckfinder_gecko.js" publishTime="09/10/2010 17:33:54" />
    <file relUrl="ckeditor/plugins/smiley/dialogs/smiley.js" publishTime="09/21/2010 16:52:06" />
    <file relUrl="ckfinder/core/images/icons/16/gif.gif" publishTime="01/11/2010 14:32:34" />
    <file relUrl="ckeditor/plugins/about/dialogs/about.js" publishTime="09/21/2010 16:52:06" />
    <file relUrl="ckfinder/core/help/es-mx/files/images/020.png" publishTime="01/11/2010 14:32:34" />
    <file relUrl="Template/default/cn/images/au_top.jpg" publishTime="06/28/2010 18:08:37" />
    <file relUrl="Template/default/en/OrderDetail.Master" publishTime="10/18/2010 11:35:33" />
    <file relUrl="ckfinder/core/images/icons/32/txt.gif" publishTime="01/11/2010 14:32:34" />
    <file relUrl="Template/default/en/Profile.Master" publishTime="10/15/2010 10:55:13" />
    <file relUrl="ckfinder/core/help/pl/files/suggestions.html" publishTime="01/04/2010 13:39:30" />
  </publishProfile>
</publishData>